SmartRemote/SmartRemote.py
SmartRemote/__init__.py
smartremote-0.1.0.dist-info/LICENSE
smartremote-0.1.0.dist-info/METADATA
smartremote-0.1.0.dist-info/WHEEL
smartremote-0.1.0.dist-info/top_level.txt
smartremote-0.1.0.dist-info/RECORD
