Metadata-Version: 2.1
Name: smartremote
Version: 0.1.0
Summary: Park Systems Python library for SPM
Home-page: https://github.com/ParkSystems-RSW/SmartRemote
Download-URL: 
Author: Park Systems
Author-email: rsw@parksystems.com
Keywords: park,systems,spm,afm
Requires-Python: >=3
License-File: LICENSE
